<?xml version="1.0" standalone="yes"?>
<PathPoints>
  <PathPoints>
    <PathPoints_ID>455f5fce-6715-4258-aac0-1623de5d7d53</PathPoints_ID>
    <PathID>Dragonfly Handler Colm=&gt;Castle Sauvage</PathID>
    <Step>2</Step>
    <X>585709</X>
    <Y>479030</Y>
    <Z>2600</Z>
    <MaxSpeed>1000</MaxSpeed>
  </PathPoints>
  <PathPoints>
    <PathPoints_ID>e0e30483-017f-4fb5-ad44-dd48cc63eab0</PathPoints_ID>
    <PathID>Dragonfly Handler Colm=&gt;Castle Sauvage</PathID>
    <Step>1</Step>
    <X>562905</X>
    <Y>512603</Y>
    <Z>2438</Z>
    <MaxSpeed>1000</MaxSpeed>
  </PathPoints>
  <PathPoints>
    <PathPoints_ID>e93b2c7e-c143-4f2e-bfb2-1d24962f5195</PathPoints_ID>
    <PathID>Yaren=&gt;North Camelot Gates</PathID>
    <Step>2</Step>
    <X>529727</X>
    <Y>478055</Y>
    <Z>2200</Z>
    <MaxSpeed>1000</MaxSpeed>
  </PathPoints>
  <PathPoints>
    <PathPoints_ID>237fe37a-a9ab-455f-92d6-d8ca94e0b9a8</PathPoints_ID>
    <PathID>Yaren=&gt;North Camelot Gates</PathID>
    <Step>1</Step>
    <X>529727</X>
    <Y>478055</Y>
    <Z>2200</Z>
    <MaxSpeed>100000</MaxSpeed>
  </PathPoints>
  <PathPoints>
    <PathPoints_ID>9e3e0762-ed3b-4d48-bad1-20a2b0253f6d</PathPoints_ID>
    <PathID>Vuloch=&gt;Ludlow</PathID>
    <Step>2</Step>
    <X>553514</X>
    <Y>512001</Y>
    <Z>2912</Z>
    <MaxSpeed>1000</MaxSpeed>
  </PathPoints>
  <PathPoints>
    <PathPoints_ID>9447f736-e40e-4ff4-87e0-375601a73e86</PathPoints_ID>
    <PathID>Vuloch=&gt;Ludlow</PathID>
    <Step>1</Step>
    <X>552957</X>
    <Y>513364</Y>
    <Z>2896</Z>
    <MaxSpeed>100000</MaxSpeed>
  </PathPoints>
  <PathPoints>
    <PathPoints_ID>12bdac5b-45eb-4812-b268-c1dc8d941554</PathPoints_ID>
    <PathID>Vuloch=&gt;Ludlow</PathID>
    <Step>3</Step>
    <X>554753</X>
    <Y>511985</Y>
    <Z>2895</Z>
    <MaxSpeed>1000</MaxSpeed>
  </PathPoints>
  <PathPoints>
    <PathPoints_ID>27920ee6-b22d-4201-a093-c9ae782306ae</PathPoints_ID>
    <PathID>Vuloch=&gt;Ludlow</PathID>
    <Step>4</Step>
    <X>557312</X>
    <Y>511706</Y>
    <Z>2368</Z>
    <MaxSpeed>1000</MaxSpeed>
  </PathPoints>
  <PathPoints>
    <PathPoints_ID>34be6ca6-4160-4ee9-9711-9c2cff9ea90b</PathPoints_ID>
    <PathID>Vuloch=&gt;Ludlow</PathID>
    <Step>5</Step>
    <X>560237</X>
    <Y>511827</Y>
    <Z>2280</Z>
    <MaxSpeed>1000</MaxSpeed>
  </PathPoints>
  <PathPoints>
    <PathPoints_ID>7c7940ca-aade-477b-85c8-2a1f97518590</PathPoints_ID>
    <PathID>Vuloch=&gt;Ludlow</PathID>
    <Step>6</Step>
    <X>562171</X>
    <Y>511296</Y>
    <Z>2300</Z>
    <MaxSpeed>1000</MaxSpeed>
  </PathPoints>
  <PathPoints>
    <PathPoints_ID>dd3d75b7-8d43-4f22-80d4-4940afe5c47a</PathPoints_ID>
    <PathID>Vuloch=&gt;Ludlow</PathID>
    <Step>7</Step>
    <X>564932</X>
    <Y>512219</Y>
    <Z>2285</Z>
    <MaxSpeed>1000</MaxSpeed>
  </PathPoints>
  <PathPoints>
    <PathPoints_ID>051f704f-5316-4483-b34d-d973682aead9</PathPoints_ID>
    <PathID>Vuloch=&gt;Ludlow</PathID>
    <Step>8</Step>
    <X>571044</X>
    <Y>511734</Y>
    <Z>2072</Z>
    <MaxSpeed>1000</MaxSpeed>
  </PathPoints>
  <PathPoints>
    <PathPoints_ID>030d6c48-7fca-4fd5-accf-23868b80ab51</PathPoints_ID>
    <PathID>Vuloch=&gt;Ludlow</PathID>
    <Step>9</Step>
    <X>571562</X>
    <Y>502883</Y>
    <Z>2119</Z>
    <MaxSpeed>1000</MaxSpeed>
  </PathPoints>
  <PathPoints>
    <PathPoints_ID>977adb01-e7db-49c4-99b9-8e6e5883a609</PathPoints_ID>
    <PathID>Vuloch=&gt;Ludlow</PathID>
    <Step>10</Step>
    <X>569147</X>
    <Y>496800</Y>
    <Z>2305</Z>
    <MaxSpeed>1000</MaxSpeed>
  </PathPoints>
  <PathPoints>
    <PathPoints_ID>f0932a46-8297-47e3-8450-d6aaf099ff2d</PathPoints_ID>
    <PathID>Vuloch=&gt;Ludlow</PathID>
    <Step>11</Step>
    <X>564382</X>
    <Y>491177</Y>
    <Z>2216</Z>
    <MaxSpeed>1000</MaxSpeed>
  </PathPoints>
  <PathPoints>
    <PathPoints_ID>9463ddc0-0c44-413d-9701-2e13b8369159</PathPoints_ID>
    <PathID>Vuloch=&gt;Ludlow</PathID>
    <Step>12</Step>
    <X>550848</X>
    <Y>490151</Y>
    <Z>2155</Z>
    <MaxSpeed>1000</MaxSpeed>
  </PathPoints>
  <PathPoints>
    <PathPoints_ID>b4edc5c3-13f3-48c6-b4a5-691e2cd242b9</PathPoints_ID>
    <PathID>Vuloch=&gt;Ludlow</PathID>
    <Step>13</Step>
    <X>540833</X>
    <Y>491185</Y>
    <Z>1888</Z>
    <MaxSpeed>1000</MaxSpeed>
  </PathPoints>
  <PathPoints>
    <PathPoints_ID>a412e6b0-1215-4294-bd62-e308389c7f84</PathPoints_ID>
    <PathID>Vuloch=&gt;Ludlow</PathID>
    <Step>14</Step>
    <X>535448</X>
    <Y>488958</Y>
    <Z>2216</Z>
    <MaxSpeed>1000</MaxSpeed>
  </PathPoints>
  <PathPoints>
    <PathPoints_ID>357cd9df-5ad9-476d-9435-8cb7f66be5b6</PathPoints_ID>
    <PathID>Vuloch=&gt;Ludlow</PathID>
    <Step>15</Step>
    <X>533657</X>
    <Y>485431</Y>
    <Z>2236</Z>
    <MaxSpeed>1000</MaxSpeed>
  </PathPoints>
  <PathPoints>
    <PathPoints_ID>b8c26cd1-b6f0-4366-bbac-dda68c49a928</PathPoints_ID>
    <PathID>Vuloch=&gt;Ludlow</PathID>
    <Step>16</Step>
    <X>531998</X>
    <Y>481126</Y>
    <Z>2200</Z>
    <MaxSpeed>1000</MaxSpeed>
  </PathPoints>
  <PathPoints>
    <PathPoints_ID>9e889af0-5d7d-4eff-b9a8-9f483bb16cf5</PathPoints_ID>
    <PathID>Vuloch=&gt;Ludlow</PathID>
    <Step>17</Step>
    <X>529969</X>
    <Y>478057</Y>
    <Z>2200</Z>
    <MaxSpeed>1000</MaxSpeed>
  </PathPoints>
  <PathPoints>
    <PathPoints_ID>9a340c19-b384-449e-884f-38f83997391e</PathPoints_ID>
    <PathID>Yaren=&gt;North Camelot Gates</PathID>
    <Step>3</Step>
    <X>525798</X>
    <Y>474331</Y>
    <Z>2227</Z>
    <MaxSpeed>1000</MaxSpeed>
  </PathPoints>
  <PathPoints>
    <PathPoints_ID>b7fc6171-03a3-4d59-a45d-9ee4903cba15</PathPoints_ID>
    <PathID>Yaren=&gt;North Camelot Gates</PathID>
    <Step>4</Step>
    <X>516909</X>
    <Y>470070</Y>
    <Z>2401</Z>
    <MaxSpeed>1000</MaxSpeed>
  </PathPoints>
  <PathPoints>
    <PathPoints_ID>e6e69632-b99e-4532-add7-2f2918c8522b</PathPoints_ID>
    <PathID>Yaren=&gt;North Camelot Gates</PathID>
    <Step>5</Step>
    <X>514993</X>
    <Y>474701</Y>
    <Z>2839</Z>
    <MaxSpeed>1000</MaxSpeed>
  </PathPoints>
  <PathPoints>
    <PathPoints_ID>70a605a4-5363-4b36-a07c-82a6ad913532</PathPoints_ID>
    <PathID>Yaren=&gt;North Camelot Gates</PathID>
    <Step>6</Step>
    <X>514759</X>
    <Y>478347</Y>
    <Z>2316</Z>
    <MaxSpeed>1000</MaxSpeed>
  </PathPoints>
  <PathPoints>
    <PathPoints_ID>2cc69b87-18c5-40a9-9a8b-bb536842f1a8</PathPoints_ID>
    <PathID>Yaren=&gt;North Camelot Gates</PathID>
    <Step>7</Step>
    <X>516846</X>
    <Y>480651</Y>
    <Z>2400</Z>
    <MaxSpeed>1000</MaxSpeed>
  </PathPoints>
  <PathPoints>
    <PathPoints_ID>fd4994a1-3653-4484-aa3b-7d5a414575e9</PathPoints_ID>
    <PathID>Yaren=&gt;North Camelot Gates</PathID>
    <Step>8</Step>
    <X>516958</X>
    <Y>494586</Y>
    <Z>3352</Z>
    <MaxSpeed>1000</MaxSpeed>
  </PathPoints>
  <PathPoints>
    <PathPoints_ID>e2e92f97-a24b-426c-91a3-e642b66ed013</PathPoints_ID>
    <PathID>Yaren=&gt;North Camelot Gates</PathID>
    <Step>9</Step>
    <X>516994</X>
    <Y>496355</Y>
    <Z>3379</Z>
    <MaxSpeed>1000</MaxSpeed>
  </PathPoints>
  <PathPoints>
    <PathPoints_ID>d1cc7786-129b-4e5c-9830-c69d1723c20d</PathPoints_ID>
    <PathID>Yaren=&gt;North Camelot Gates</PathID>
    <Step>10</Step>
    <X>515854</X>
    <Y>496791</Y>
    <Z>3352</Z>
    <MaxSpeed>1000</MaxSpeed>
  </PathPoints>
  <PathPoints>
    <PathPoints_ID>749e953b-111c-43a2-96c5-587202edaa24</PathPoints_ID>
    <PathID>Uliam=&gt;Camelot Hills</PathID>
    <Step>1</Step>
    <X>585594</X>
    <Y>479122</Y>
    <Z>2609</Z>
    <MaxSpeed>100000</MaxSpeed>
  </PathPoints>
  <PathPoints>
    <PathPoints_ID>2c2065df-9a61-4b7d-b73e-dbdf220572c9</PathPoints_ID>
    <PathID>Uliam=&gt;Camelot Hills</PathID>
    <Step>2</Step>
    <X>585594</X>
    <Y>479122</Y>
    <Z>2609</Z>
    <MaxSpeed>1000</MaxSpeed>
  </PathPoints>
  <PathPoints>
    <PathPoints_ID>299b4d56-ef6f-472c-808b-da0fc1d1821c</PathPoints_ID>
    <PathID>Uliam=&gt;Camelot Hills</PathID>
    <Step>3</Step>
    <X>585248</X>
    <Y>481710</Y>
    <Z>2238</Z>
    <MaxSpeed>1000</MaxSpeed>
  </PathPoints>
  <PathPoints>
    <PathPoints_ID>8718a401-c021-490e-b281-98be9d82dfec</PathPoints_ID>
    <PathID>Uliam=&gt;Camelot Hills</PathID>
    <Step>4</Step>
    <X>585524</X>
    <Y>483696</Y>
    <Z>2241</Z>
    <MaxSpeed>1000</MaxSpeed>
  </PathPoints>
  <PathPoints>
    <PathPoints_ID>de0eb4d5-e8c6-452a-9a73-3a7292a16b3a</PathPoints_ID>
    <PathID>Uliam=&gt;Camelot Hills</PathID>
    <Step>5</Step>
    <X>584258</X>
    <Y>487442</Y>
    <Z>2292</Z>
    <MaxSpeed>1000</MaxSpeed>
  </PathPoints>
  <PathPoints>
    <PathPoints_ID>13e5f3e4-6b06-4fbf-8624-657cbf91c644</PathPoints_ID>
    <PathID>Uliam=&gt;Camelot Hills</PathID>
    <Step>6</Step>
    <X>583711</X>
    <Y>492791</Y>
    <Z>2192</Z>
    <MaxSpeed>1000</MaxSpeed>
  </PathPoints>
  <PathPoints>
    <PathPoints_ID>24b8cad0-946d-45c5-b627-ad25f5652d2a</PathPoints_ID>
    <PathID>Uliam=&gt;Camelot Hills</PathID>
    <Step>7</Step>
    <X>583111</X>
    <Y>493911</Y>
    <Z>2192</Z>
    <MaxSpeed>1000</MaxSpeed>
  </PathPoints>
  <PathPoints>
    <PathPoints_ID>cbf32f05-a984-4d5b-a081-24df6b529073</PathPoints_ID>
    <PathID>Uliam=&gt;Camelot Hills</PathID>
    <Step>8</Step>
    <X>582859</X>
    <Y>495248</Y>
    <Z>2192</Z>
    <MaxSpeed>1000</MaxSpeed>
  </PathPoints>
  <PathPoints>
    <PathPoints_ID>29a08b34-b55f-4892-8e66-848fb449a0bc</PathPoints_ID>
    <PathID>Uliam=&gt;Camelot Hills</PathID>
    <Step>9</Step>
    <X>583511</X>
    <Y>497842</Y>
    <Z>2192</Z>
    <MaxSpeed>1000</MaxSpeed>
  </PathPoints>
  <PathPoints>
    <PathPoints_ID>ee56fde9-7e47-484e-aaf6-2c1be45e3a29</PathPoints_ID>
    <PathID>Uliam=&gt;Camelot Hills</PathID>
    <Step>10</Step>
    <X>584182</X>
    <Y>498450</Y>
    <Z>2192</Z>
    <MaxSpeed>1000</MaxSpeed>
  </PathPoints>
  <PathPoints>
    <PathPoints_ID>2e22c6b8-941e-49db-bb81-03905285063c</PathPoints_ID>
    <PathID>Uliam=&gt;Camelot Hills</PathID>
    <Step>11</Step>
    <X>585226</X>
    <Y>498677</Y>
    <Z>2192</Z>
    <MaxSpeed>1000</MaxSpeed>
  </PathPoints>
  <PathPoints>
    <PathPoints_ID>bc998168-ef32-4476-ace7-54dcc262d89b</PathPoints_ID>
    <PathID>Uliam=&gt;Camelot Hills</PathID>
    <Step>12</Step>
    <X>585989</X>
    <Y>502453</Y>
    <Z>2112</Z>
    <MaxSpeed>1000</MaxSpeed>
  </PathPoints>
  <PathPoints>
    <PathPoints_ID>97646dcd-e461-4b4a-bb4e-23831ff1e2d3</PathPoints_ID>
    <PathID>Uliam=&gt;Camelot Hills</PathID>
    <Step>13</Step>
    <X>586885</X>
    <Y>503822</Y>
    <Z>2112</Z>
    <MaxSpeed>1000</MaxSpeed>
  </PathPoints>
  <PathPoints>
    <PathPoints_ID>d64c4d37-eacd-4738-a280-958d9c223da7</PathPoints_ID>
    <PathID>Uliam=&gt;Camelot Hills</PathID>
    <Step>14</Step>
    <X>587106</X>
    <Y>506934</Y>
    <Z>2112</Z>
    <MaxSpeed>1000</MaxSpeed>
  </PathPoints>
  <PathPoints>
    <PathPoints_ID>3feefcf8-5f8e-46b3-aab4-723fb7558bda</PathPoints_ID>
    <PathID>Uliam=&gt;Camelot Hills</PathID>
    <Step>15</Step>
    <X>586022</X>
    <Y>510058</Y>
    <Z>2204</Z>
    <MaxSpeed>1000</MaxSpeed>
  </PathPoints>
  <PathPoints>
    <PathPoints_ID>eb7f625f-150d-44e3-9987-8dcaac8b0ee1</PathPoints_ID>
    <PathID>Uliam=&gt;Camelot Hills</PathID>
    <Step>16</Step>
    <X>586296</X>
    <Y>512660</Y>
    <Z>2192</Z>
    <MaxSpeed>1000</MaxSpeed>
  </PathPoints>
  <PathPoints>
    <PathPoints_ID>778afbc8-c116-4764-9bcc-9dccff5ba29f</PathPoints_ID>
    <PathID>Uliam=&gt;Camelot Hills</PathID>
    <Step>17</Step>
    <X>582753</X>
    <Y>512761</Y>
    <Z>2072</Z>
    <MaxSpeed>1000</MaxSpeed>
  </PathPoints>
  <PathPoints>
    <PathPoints_ID>8e392ccf-7b13-4799-8b36-18d702cee26c</PathPoints_ID>
    <PathID>Uliam=&gt;Camelot Hills</PathID>
    <Step>18</Step>
    <X>582062</X>
    <Y>513533</Y>
    <Z>2072</Z>
    <MaxSpeed>1000</MaxSpeed>
  </PathPoints>
  <PathPoints>
    <PathPoints_ID>836561aa-e4f4-462d-9704-fea80de5328b</PathPoints_ID>
    <PathID>Uliam=&gt;Camelot Hills</PathID>
    <Step>19</Step>
    <X>581443</X>
    <Y>516055</Y>
    <Z>2072</Z>
    <MaxSpeed>1000</MaxSpeed>
  </PathPoints>
  <PathPoints>
    <PathPoints_ID>6d3a04a9-c03b-434f-8d0b-f27d694d7b56</PathPoints_ID>
    <PathID>Uliam=&gt;Camelot Hills</PathID>
    <Step>20</Step>
    <X>580760</X>
    <Y>516904</Y>
    <Z>2072</Z>
    <MaxSpeed>1000</MaxSpeed>
  </PathPoints>
  <PathPoints>
    <PathPoints_ID>05774ad0-29a1-45fc-8a79-04ca8e83593f</PathPoints_ID>
    <PathID>Uliam=&gt;Camelot Hills</PathID>
    <Step>21</Step>
    <X>577513</X>
    <Y>517128</Y>
    <Z>2075</Z>
    <MaxSpeed>1000</MaxSpeed>
  </PathPoints>
  <PathPoints>
    <PathPoints_ID>5c6a7ba9-ff8b-42c8-96b6-3f2bfe41c3ab</PathPoints_ID>
    <PathID>Uliam=&gt;Camelot Hills</PathID>
    <Step>22</Step>
    <X>572200</X>
    <Y>516277</Y>
    <Z>2096</Z>
    <MaxSpeed>1000</MaxSpeed>
  </PathPoints>
  <PathPoints>
    <PathPoints_ID>03b3359b-9064-4b8b-b28d-7578152b6879</PathPoints_ID>
    <PathID>Uliam=&gt;Camelot Hills</PathID>
    <Step>23</Step>
    <X>571728</X>
    <Y>515762</Y>
    <Z>2072</Z>
    <MaxSpeed>1000</MaxSpeed>
  </PathPoints>
  <PathPoints>
    <PathPoints_ID>8ce405ba-437a-453f-b042-58a1af148158</PathPoints_ID>
    <PathID>Uliam=&gt;Camelot Hills</PathID>
    <Step>24</Step>
    <X>571616</X>
    <Y>512988</Y>
    <Z>2072</Z>
    <MaxSpeed>1000</MaxSpeed>
  </PathPoints>
  <PathPoints>
    <PathPoints_ID>6617ef75-e6b4-4a84-944e-5a40ac10f4b9</PathPoints_ID>
    <PathID>Uliam=&gt;Camelot Hills</PathID>
    <Step>25</Step>
    <X>570821</X>
    <Y>512530</Y>
    <Z>2072</Z>
    <MaxSpeed>1000</MaxSpeed>
  </PathPoints>
  <PathPoints>
    <PathPoints_ID>1f94a1c2-bd4c-4863-a8a6-6aaa13283811</PathPoints_ID>
    <PathID>Uliam=&gt;Camelot Hills</PathID>
    <Step>26</Step>
    <X>571473</X>
    <Y>509825</Y>
    <Z>2118</Z>
    <MaxSpeed>1000</MaxSpeed>
  </PathPoints>
  <PathPoints>
    <PathPoints_ID>7a643863-faee-4db9-84fb-2319b3fe4a5f</PathPoints_ID>
    <PathID>Uliam=&gt;Camelot Hills</PathID>
    <Step>27</Step>
    <X>571271</X>
    <Y>507051</Y>
    <Z>2151</Z>
    <MaxSpeed>1000</MaxSpeed>
  </PathPoints>
  <PathPoints>
    <PathPoints_ID>ebf1a510-8f10-47c9-af30-503e710f8f7f</PathPoints_ID>
    <PathID>Uliam=&gt;Camelot Hills</PathID>
    <Step>28</Step>
    <X>572460</X>
    <Y>504634</Y>
    <Z>2184</Z>
    <MaxSpeed>1000</MaxSpeed>
  </PathPoints>
</PathPoints>
